README.md
requirements-dev.txt
requirements.txt
setup.py
sourcer/__init__.py
sourcer/grammar.py
sourcer/parser.py
sourcer/translator.py
sourcer.egg-info/PKG-INFO
sourcer.egg-info/SOURCES.txt
sourcer.egg-info/dependency_links.txt
sourcer.egg-info/requires.txt
sourcer.egg-info/top_level.txt
sourcer/expressions/__init__.py
sourcer/expressions/apply.py
sourcer/expressions/base.py
sourcer/expressions/byte.py
sourcer/expressions/call.py
sourcer/expressions/choice.py
sourcer/expressions/class_.py
sourcer/expressions/constants.py
sourcer/expressions/discard.py
sourcer/expressions/expect.py
sourcer/expressions/fail.py
sourcer/expressions/inline_python.py
sourcer/expressions/let.py
sourcer/expressions/list.py
sourcer/expressions/longest.py
sourcer/expressions/operator_table.py
sourcer/expressions/opt.py
sourcer/expressions/ref.py
sourcer/expressions/regex.py
sourcer/expressions/rule.py
sourcer/expressions/sep.py
sourcer/expressions/seq.py
sourcer/expressions/skip.py
sourcer/expressions/str.py
sourcer/expressions/sugar.py
sourcer/expressions/utils.py
sourcer/expressions/where.py