Metadata-Version: 2.1
Name: sourcer
Version: 0.5.0
Summary: simple parsing library
Home-page: https://github.com/jvs/sourcer
Author: jvs
Author-email: vonseg@protonmail.com
License: MIT License
Keywords: packrat,parser,peg
Platform: any
Classifier: Development Status :: 2 - Pre-Alpha
Classifier: Topic :: Software Development :: Interpreters
Classifier: Topic :: Software Development :: Compilers
Classifier: License :: OSI Approved :: MIT License
Classifier: Programming Language :: Python
Requires-Python: >=3.6
